.gitignore
MANIFEST.in
README.md
setup.py
hermes/__init__.py
hermes/chatserver.py
hermes/database.py
hermes_chat.egg-info/PKG-INFO
hermes_chat.egg-info/SOURCES.txt
hermes_chat.egg-info/dependency_links.txt
hermes_chat.egg-info/not-zip-safe
hermes_chat.egg-info/requires.txt
hermes_chat.egg-info/top_level.txt