Metadata-Version: 1.0
Name: hermes-chat
Version: 0.2.0
Summary: A simple python-based group chat server built on XMPP.
Home-page: https://github.com/mattlong/hermes
Author: Matt Long
Author-email: matt@mattlong.org
License: BSD
Platform: UNKNOWN
Classifier: Programming Language :: Python
Classifier: Programming Language :: Python :: 2
Classifier: Operating System :: Unix
Classifier: Development Status :: 3 - Alpha
Classifier: Intended Audience :: Developers
Classifier: Intended Audience :: System Administrators
Classifier: Topic :: Software Development :: Libraries :: Python Modules
